pythontuio/__init__.py
pythontuio/const.py
pythontuio/dispatcher.py
pythontuio/tuio.py
pythontuio/tuio_profiles.py
python_tuio-0.0.9.dist-info/LICENSE.txt
python_tuio-0.0.9.dist-info/METADATA
python_tuio-0.0.9.dist-info/WHEEL
python_tuio-0.0.9.dist-info/top_level.txt
python_tuio-0.0.9.dist-info/RECORD
