Metadata-Version: 2.1
Name: python-tuio
Version: 0.0.9
Summary: python3 implementation of the TUIO protocol
Home-page: https://github.com/tweigel-dev/python-tuio
Author: tweigel-dev
Author-email: weigel-thomas@outlook.de
License: UNKNOWN
Platform: UNKNOWN
Classifier: Programming Language :: Python :: 3
Classifier: License :: OSI Approved :: MIT License
Classifier: Operating System :: OS Independent
Requires-Python: >=3.6
